Shiboken/QtCore4.dll
Shiboken/QtXml4.dll
Shiboken/shiboken-python3.3.dll
Shiboken/shiboken-python3.3.lib
Shiboken/shiboken.exe
Shiboken/shiboken.pyd
Shiboken/__init__.py
Shiboken/docs/shiboken/.buildinfo
Shiboken/docs/shiboken/codeinjectionsemantics.html
Shiboken/docs/shiboken/commandlineoptions.html
Shiboken/docs/shiboken/contents.html
Shiboken/docs/shiboken/faq.html
Shiboken/docs/shiboken/index.html
Shiboken/docs/shiboken/objects.inv
Shiboken/docs/shiboken/overview.html
Shiboken/docs/shiboken/ownership.html
Shiboken/docs/shiboken/projectfile.html
Shiboken/docs/shiboken/search.html
Shiboken/docs/shiboken/searchindex.js
Shiboken/docs/shiboken/sequenceprotocol.html
Shiboken/docs/shiboken/shibokenmodule.html
Shiboken/docs/shiboken/typeconverters.html
Shiboken/docs/shiboken/typesystemvariables.html
Shiboken/docs/shiboken/wordsofadvice.html
Shiboken/docs/shiboken/.doctrees/codeinjectionsemantics.doctree
Shiboken/docs/shiboken/.doctrees/commandlineoptions.doctree
Shiboken/docs/shiboken/.doctrees/contents.doctree
Shiboken/docs/shiboken/.doctrees/environment.pickle
Shiboken/docs/shiboken/.doctrees/faq.doctree
Shiboken/docs/shiboken/.doctrees/overview.doctree
Shiboken/docs/shiboken/.doctrees/ownership.doctree
Shiboken/docs/shiboken/.doctrees/projectfile.doctree
Shiboken/docs/shiboken/.doctrees/sequenceprotocol.doctree
Shiboken/docs/shiboken/.doctrees/shibokenmodule.doctree
Shiboken/docs/shiboken/.doctrees/typeconverters.doctree
Shiboken/docs/shiboken/.doctrees/typesystemvariables.doctree
Shiboken/docs/shiboken/.doctrees/wordsofadvice.doctree
Shiboken/docs/shiboken/_images/bindinggen-development.png
Shiboken/docs/shiboken/_images/boostqtarch.png
Shiboken/docs/shiboken/_images/converter.png
Shiboken/docs/shiboken/_sources/codeinjectionsemantics.txt
Shiboken/docs/shiboken/_sources/commandlineoptions.txt
Shiboken/docs/shiboken/_sources/contents.txt
Shiboken/docs/shiboken/_sources/faq.txt
Shiboken/docs/shiboken/_sources/overview.txt
Shiboken-1.2.2.dist-info/DESCRIPTION.rst
Shiboken-1.2.2.dist-info/METADATA
Shiboken-1.2.2.dist-info/metadata.json
Shiboken-1.2.2.dist-info/RECORD
Shiboken-1.2.2.dist-info/top_level.txt
Shiboken-1.2.2.dist-info/WHEEL
